src/__init__.py
src/main.py
Money_Control_Scrap-0.1.2.dist-info/METADATA
Money_Control_Scrap-0.1.2.dist-info/WHEEL
Money_Control_Scrap-0.1.2.dist-info/entry_points.txt
Money_Control_Scrap-0.1.2.dist-info/top_level.txt
Money_Control_Scrap-0.1.2.dist-info/RECORD
