Metadata-Version: 2.1
Name: Money_Control_Scrap
Version: 0.1.2
Summary: A package to scrape news from Money Control
Author: Aniruddha Kumar
Author-email: foraniruddhakumar@gmail.com
Requires-Dist: selenium
Requires-Dist: pandas
